{
  "last_updated": "2026-04-15T13:24:35.471936",
  "items": [
    {
      "keyword": "상장지수 펀드",
      "category": "",
      "timestamp": "2026-04-15T13:24:35.471916"
    },
    {
      "keyword": "홍지윤",
      "category": "",
      "timestamp": "2026-04-15T13:24:35.471926"
    },
    {
      "keyword": "스리랑카",
      "category": "",
      "timestamp": "2026-04-15T13:24:35.471927"
    },
    {
      "keyword": "심혜진",
      "category": "",
      "timestamp": "2026-04-15T13:24:35.471929"
    },
    {
      "keyword": "배현진",
      "category": "",
      "timestamp": "2026-04-15T13:24:35.471930"
    },
    {
      "keyword": "김서라",
      "category": "",
      "timestamp": "2026-04-15T13:24:35.471931"
    },
    {
      "keyword": "항공",
      "category": "",
      "timestamp": "2026-04-15T13:24:35.471932"
    },
    {
      "keyword": "안치홍",
      "category": "",
      "timestamp": "2026-04-15T13:24:35.471933"
    },
    {
      "keyword": "맹승지",
      "category": "",
      "timestamp": "2026-04-15T13:24:35.471934"
    },
    {
      "keyword": "홍해",
      "category": "",
      "timestamp": "2026-04-15T13:24:35.471935"
    }
  ]
}